hellotest_ire/__init__.py
hellotest_ire/emon.py
hellotest_ire/version.py
hellotest_ire-0.0.3.dist-info/licenses/LICENSE
hellotest_ire-0.0.3.dist-info/METADATA
hellotest_ire-0.0.3.dist-info/WHEEL
hellotest_ire-0.0.3.dist-info/top_level.txt
hellotest_ire-0.0.3.dist-info/RECORD
